{
    "$schema": "http://json-schema.org/draft-07/schema#",
    "$id": "315169571",
    "x-format-version": "MISSING VERSION",
    "x-minecraft-version": "1.26.0",
    "x-protocol-version": 924,
    "title": "ChunkRadiusUpdatedPacket",
    "description": "Sent when the world is loading. We don't know why it is sent four times. Defines the tick distance.",
    "type": "object",
    "properties": {
        "Chunk Radius": {
            "type": "integer",
            "x-underlying-type": "int32",
            "x-serialization-options": [
                "Compression"
            ],
            "x-ordinal-index": 0
        }
    },
    "required": [
        "Chunk Radius"
    ],
    "$metaProperties": {
        "[cereal:packet]": 70,
        "[cereal:packet_details]": ""
    }
}