{
    "$schema": "http://json-schema.org/draft-07/schema#",
    "$id": "3441939962",
    "x-format-version": "MISSING VERSION",
    "x-minecraft-version": "1.26.0",
    "x-protocol-version": 924,
    "title": "GuiDataPickItemPacket",
    "description": "The server telling the client what item slot to hover over in the hotbar.",
    "type": "object",
    "properties": {
        "Item Effect Name": {
            "type": "string",
            "x-ordinal-index": 1
        },
        "Item Name": {
            "type": "string",
            "x-ordinal-index": 0
        },
        "Slot": {
            "type": "integer",
            "x-underlying-type": "int32",
            "x-ordinal-index": 2
        }
    },
    "required": [
        "Item Effect Name",
        "Item Name",
        "Slot"
    ],
    "$metaProperties": {
        "[cereal:packet]": 54,
        "[cereal:packet_details]": "This is only used when players use pick block, a command is used, tests, and some 3rd party content."
    }
}